imlazy_photo/__init__.py
imlazy_photo/__main__.py
imlazy_photo/imlazy_photo.py
imlazy_photo-1.0.2.dist-info/METADATA
imlazy_photo-1.0.2.dist-info/WHEEL
imlazy_photo-1.0.2.dist-info/top_level.txt
imlazy_photo-1.0.2.dist-info/RECORD
