Metadata-Version: 2.1
Name: imlazy-photo
Version: 1.0.2
Summary: Make directory and put in photo
Home-page: https://github.com/cosmos2/imlazy_photo
Author: cosmos2
Author-email: playnstop.s@gmail.com
License: UNKNOWN
Platform: UNKNOWN
Classifier: Programming Language :: Python :: 3
Requires-Python: >=3.7
